patient_trajectory/__init__.py
patient_trajectory/visualization.py
patient_trajectory-1.0.dist-info/LICENSE
patient_trajectory-1.0.dist-info/METADATA
patient_trajectory-1.0.dist-info/WHEEL
patient_trajectory-1.0.dist-info/top_level.txt
patient_trajectory-1.0.dist-info/RECORD
