Metadata-Version: 2.1
Name: patient-trajectory
Version: 1.0
Summary: A package designed to visualize patient trajectories for multiple patients, featuring Gantt-style plots to represent patient episodes.
Home-page: https://github.com/dipendrapant/patient_trajectory
Author: Dipendra Pant
Author-email: dipendrapant778@gmail.com
License: UNKNOWN
Platform: UNKNOWN
Classifier: Programming Language :: Python :: 3
Classifier: License :: OSI Approved :: MIT License
Classifier: Operating System :: OS Independent
Requires-Python: >=3.6
License-File: LICENSE
Requires-Dist: numpy
Requires-Dist: pandas
Requires-Dist: matplotlib
